odoo/addons/account_reconciliation_widget_limit_aml/README.rst
odoo/addons/account_reconciliation_widget_limit_aml/__init__.py
odoo/addons/account_reconciliation_widget_limit_aml/__manifest__.py
odoo/addons/account_reconciliation_widget_limit_aml/i18n/account_reconciliation_widget_limit_aml.pot
odoo/addons/account_reconciliation_widget_limit_aml/i18n/es.po
odoo/addons/account_reconciliation_widget_limit_aml/i18n/sv.po
odoo/addons/account_reconciliation_widget_limit_aml/models/__init__.py
odoo/addons/account_reconciliation_widget_limit_aml/models/reconciliation_widget.py
odoo/addons/account_reconciliation_widget_limit_aml/models/res_company.py
odoo/addons/account_reconciliation_widget_limit_aml/models/res_config_settings.py
odoo/addons/account_reconciliation_widget_limit_aml/readme/CONTRIBUTORS.rst
odoo/addons/account_reconciliation_widget_limit_aml/readme/DESCRIPTION.rst
odoo/addons/account_reconciliation_widget_limit_aml/readme/USAGE.rst
odoo/addons/account_reconciliation_widget_limit_aml/static/description/icon.png
odoo/addons/account_reconciliation_widget_limit_aml/static/description/index.html
odoo/addons/account_reconciliation_widget_limit_aml/views/res_config_settings_views.xml
odoo14_addon_account_reconciliation_widget_limit_aml-14.0.1.0.1.dev8.dist-info/METADATA
odoo14_addon_account_reconciliation_widget_limit_aml-14.0.1.0.1.dev8.dist-info/WHEEL
odoo14_addon_account_reconciliation_widget_limit_aml-14.0.1.0.1.dev8.dist-info/top_level.txt
odoo14_addon_account_reconciliation_widget_limit_aml-14.0.1.0.1.dev8.dist-info/RECORD
